Metadata-Version: 2.1
Name: sih
Version: 0.1
Summary: Subimage highlighter
Home-page: https://github.com/ShadowCodeCz/subimage_highlighter
Author: ShadowCodeCz
Author-email: shadow.code.cz@gmail.com
License: GNU Affero General Public License v3 or later (AGPLv3+)
Project-URL: Source, https://github.com/ShadowCodeCz/subimage_highlighter
Project-URL: Tracker, https://github.com/ShadowCodeCz/subimage_highlighter/issues
Keywords: subimage highlighter
Platform: UNKNOWN
Classifier: Development Status :: 5 - Production/Stable
Classifier: Intended Audience :: Developers
Classifier: Programming Language :: Python :: 3.6
Classifier: Programming Language :: Python :: 3.7
Classifier: Programming Language :: Python :: 3.8
Classifier: Programming Language :: Python :: 3.9
Classifier: License :: OSI Approved :: GNU Affero General Public License v3 or later (AGPLv3+)
Classifier: Operating System :: OS Independent
